boots/__init__.py
boots/core.py
boots-0.1.2.dist-info/WHEEL
boots-0.1.2.dist-info/METADATA
boots-0.1.2.dist-info/RECORD
