Metadata-Version: 2.1
Name: boots
Version: 0.1.2
Summary: A tiny statistical bootstraping library.
Author: Peter Baumgartner
Author-email: 5107405+pmbaumgartner@users.noreply.github.com
Requires-Python: >=3.8,<4.0
Classifier: Programming Language :: Python :: 3
Classifier: Programming Language :: Python :: 3.8
Classifier: Programming Language :: Python :: 3.9
Classifier: Programming Language :: Python :: 3.10
Classifier: Programming Language :: Python :: 3.11
Requires-Dist: joblib (>=1.2.0,<2.0.0)
Requires-Dist: numpy (>=1.23.4,<2.0.0)
Requires-Dist: vose (>=0.0.1,<0.0.2)
